aideploy/__init__.py
aideploy/__main__.py
aideploy-0.0.1.dev1.dist-info/METADATA
aideploy-0.0.1.dev1.dist-info/WHEEL
aideploy-0.0.1.dev1.dist-info/entry_points.txt
aideploy-0.0.1.dev1.dist-info/licenses/LICENSE
aideploy-0.0.1.dev1.dist-info/RECORD
