Metadata-Version: 2.4
Name: aideploy
Version: 0.0.1.dev1
Summary: Deploy vibing.
License-Expression: MIT
License-File: LICENSE
Keywords: ai,automation,deployment,devops
Classifier: License :: OSI Approved :: MIT License
Classifier: Programming Language :: Python :: 3
Requires-Python: >=3.10
Requires-Dist: pyyaml>=6.0.3
Requires-Dist: ruff>=0.14.11
